Workbook
Name DadosExternos_1: Jira_consulta!$A$1:$J$22
Name DadosExternos_2: 'Função Invocada'!$A$1

Sheet LEIA-ME
A1: Planilha do Aluno/Equipe — Projeto de Extensão
A2: Prática de Gestão de Projetos · Fatec São Roque · ODS 9, 12 e 17
A4: COMO USAR
A5: 1 | B5: Esta planilha pertence a UMA equipe/projeto.
A6: 2 | B6: Preencha somente as células amarelas. Células brancas/cinzas podem conter fórmulas.
A7: 3 | B7: Use o mesmo projeto durante todo o semestre; os artefatos são acumulativos.
A8: 4 | B8: Registre evidências por link/arquivo e mantenha o professor com acesso ao board Kanban e à pasta de evidências.
A9: 5 | B9: A aba Requisitos deve conter a meta numerada do ODS quando houver vínculo (ex.: 12.5, 9.3, 17.17).
A10: 6 | B10: O diário operacional pode ficar no Jira; esta planilha consolida gestão, horas, indicadores e evidências. Jira_consulta é a consulta de leitura; o vínculo individual e os comandos de sincronização ficam na aba 9. Backlog-Sprints.
A11: 7 | B11: O diário operacional pode ficar no Jira; esta planilha consolida gestão, horas, indicadores e evidências.
A13: ABAS E FINALIDADE
A14: 1. Identificação | B14: Equipe, parceiro, sponsor, gerente, ODS e dados gerais.
A15: 2. TAP | B15: Problema, justificativa, objetivos SMART, premissas, restrições e sucesso.
A16: 3. Stakeholders | B16: Poder, interesse, atitude, estratégia e comunicação.
A17: 4. Requisitos | B17: Requisitos, aceitação, prioridade, origem e vínculo ODS/meta.
A18: 5. EAP-RACI | B18: Entregas, pacotes de trabalho, esforço e responsabilidades.
A19: 6. Cronograma | B19: Planejado x real, dependências e progresso.
A20: 7. Orçamento | B20: Custos previstos/reais, variações e cotações.
A21: 8. Riscos | B21: Probabilidade, impacto, exposição, resposta e gatilho.
A22: 9. Backlog-Sprints | B22: Épicos, histórias, tarefas, sprint, prioridade e status.
A23: 10. Horas Extensão | B23: Horas em aula e extraclasse, alunos e evidências.
A24: 11. Mudanças | B24: Solicitações e impactos em escopo, prazo, custo e qualidade.
A25: 12. Qualidade-Testes | B25: Critérios de aceitação, casos de teste e resultado.
... A30: Dashboard | B30: Resumo executivo do projeto.

Sheet 1. Identificação
A1: Identificação do Projeto
A2: Preencher no início do semestre e revisar quando necessário
A4: DADOS DO PROJETO
A5: Nome do projeto | B5: PisoFácil | C5: Papel | D5: Nome | E5: Responsabilidade principal
A6: Nome da equipe/empresa | B6: Equipe discente PisoFácil — Fatec São Roque (Sistemas para Internet, 4º semestre) | C6: Gerente do projeto | D6: Arthur Laranjeira | E6: Integrar planejamento, acompanhar cronograma, riscos, comunicação e evidências; relacionamento com o parceiro
A7: Organização parceira | B7: Daniel Laranjeira — Restauração de Pisos de Madeira (profissional autônomo, Ibiúna/SP) | C7: Produto/Protótipo | D7: Gabriel Candido | E7: Wireframe e protótipo da landing page; testes cross-browser
A8: Responsável do parceiro | B8: Daniel Laranjeira (proprietário/autônomo); responsável de contato: Arthur Laranjeira | C8: Mercado e Negócio | D8: Lucas De Gois | E8: Mercado e negócio; estruturação do backlog de requisitos e tarefas
A9: E-mail/contato | B9: Contato via Arthur Laranjeira (responsável de contato); reuniões presenciais em Ibiúna/SP | C9: Finanças | D9: João Lucas | E9: Orçamento de referência, ferramentas de custo zero e backlog de requisitos e tarefas
A10: Sponsor institucional | B10: Prof. Sandro Amâncio de Sá — Docente / Sponsor institucional / PMO (Fatec São Roque) | C10: Docente / Sponsor / PMO | D10: Prof. Sandro Amâncio de Sá | E10: Orientar, acompanhar a governança e aprovar mudanças acadêmicas
A11: Gerente do projeto (aluno) | B11: Arthur Laranjeira
A12: Demais integrantes | B12: Lucas De Gois; Gabriel Candido; João Lucas
A13: ODS principal | B13: ODS 9;12;17
A14: Meta(s) ODS prioritária(s) | B14: 9.c (OBJ-01, RF-01, RNF-01); 12.5 (OBJ-02, RF-02); 17.17 (OBJ-03, RF-03)
A15: Data de início | B15: 46252
A16: Data prevista de término | B16: 46341
A17: Link do Jira/Kanban | B17: Quadro Trello/Kanban (estruturação prevista para 01/09/2026)
A18: Pasta de evidências | B18: Pasta Google Drive — Repositório Documental do Projeto
A19: Repositório GitHub | B19: A definir — publicação prevista em plataforma gratuita (GitHub Pages / Vercel / Netlify)
A20: Protótipo/Figma | B20: Link Figma — wireframe/protótipo de baixa fidelidade (previsto para 05/09/2026)
A21: Homologação/MVP | B21: MVP/testes previsto para 20/10/2026 — publicação com domínio temporário gratuito

Sheet 2. TAP
A1: Termo de Abertura do Projeto (TAP)
A2: Base para autorização formal e validação do escopo
A4: 1. Problema e justificativa
A5: Problema: embora o profissional autônomo Daniel Laranjeira já possua demanda ativa no segmento especializado de restauração e revitalização de pisos de madeira, sua atuação carece de canais digitais oficiais de divulgação e apresentação. A necessidade é ampliar a visibilidade de mercado e profissionalizar a vitrine dos serviços em Ibiúna e região, para que proprietários de residências, sítios e chácaras encontrem o trabalho na internet e vejam a qualidade técnica das restaurações. Evidências: reunião diagnóstica presencial, inexistência de portfólio visual digital, ausência de catálogo online com fotos de antes/depois. Problema confirmado pelo parceiro. Justificativa: a restauração de pisos de madeira nobre evita o descarte desnecessário de matéria-prima (economia circular e consumo sustentável); uma presença digital moderna fortalece a autoridade técnica do profissional e facilita a demonstração de projetos anteriores. Benefício esperado: maior visibilidade da marca, canal direto via WhatsApp, valorização do trabalho técnico local e facilidade para donos de imóveis encontrarem mão de obra qualificada na região.
A10: 2. Produto/MVP e resultados esperados
A11: PisoFácil: landing page responsiva de apresentação profissional (Home, Sobre, Serviços, Galeria, Contato), com galeria interativa 'Antes e Depois', botões de CTA para o WhatsApp comercial, SEO básico local (Ibiúna e região) e hospedagem do MVP em ambiente web acessível. Nível: protótipo/MVP acadêmico validado em ambiente controlado ou de homologação. Fora do escopo: agendamento online automatizado com painel administrativo, pagamento/checkout ou e-commerce, gestão de anúncios pagos (Google Ads / Meta Ads) e aplicativo nativo (Android/iOS). Orçamento de referência: R$ 0,00.
A16: 3. Objetivos SMART
A17: # | B17: Objetivo SMART | C17: Indicador | D17: Valor-base | E17: Meta | F17: Prazo | G17: ODS/meta
A18: 1 | B18: OBJ-01 — Desenvolver e publicar uma landing page responsiva de divulgação do serviço até o encerramento do semestre | C18: Site publicado, 100% responsivo e com carregamento em menos de 3 s | D18: Sem canais digitais oficiais de divulgação | E18: Site publicado e responsivo, carregando em < 3 s | F18: Encerramento — 15/11/2026 | G18: ODS 9 (9.c)
A19: 2 | B19: OBJ-02 — Criar catálogo interativo com no mínimo 6 projetos de restauro (antes e depois) | C19: Galeria funcional e aprovada pelo parceiro no teste de usabilidade | D19: Sem portfólio visual digital nem catálogo de antes/depois | E19: Galeria com ≥ 6 projetos aprovada pelo parceiro | F19: MVP/testes — 20/10/2026 | G19: ODS 12 (12.5)
A20: 3 | B20: OBJ-03 — Estruturar canal ágil de captação comercial integrado diretamente ao WhatsApp | C20: Taxa de acionamento do CTA/WhatsApp nos testes de clique | D20: Sem canal digital de captação | E20: CTA/WhatsApp validado em 100% dos testes de clique | F20: MVP/testes — 20/10/2026 | G20: ODS 17 (17.17)
A21: 4
A22: 5
A23: 6
A25: 4. Premissas e restrições
A26: Tipo | B26: Descrição | C26: Impacto se não atendida | D26: Responsável | E26: Status | F26: Evidência | G26: Observação
A27: Premissa | B27: O parceiro fornecerá fotos de boa qualidade das obras anteriores para compor a galeria. | C27: Galeria incompleta e atraso no protótipo | D27: Arthur Laranjeira / Daniel Laranjeira | F27: Ata de Validação de Escopo e TAP v1.2 (18/08/2026) | G27: Coleta inicial de fotos prevista para 25/08/2026
A28: Premissa | B28: O canal de atendimento via WhatsApp será operado continuamente pelo profissional. | C28: Contatos gerados pelo site sem resposta | D28: Daniel Laranjeira | F28: Ata de Validação de Escopo e TAP v1.2 (18/08/2026)
A29: Restrição | B29: Prazo estrito delimitado pelo calendário acadêmico do 2º semestre letivo de 2026. | D29: Equipe discente | F29: Ata de Validação de Escopo e TAP v1.2 (18/08/2026) | G29: Encerramento previsto para 15/11/2026
A30: Restrição | B30: Uso de ferramentas gratuitas ou de custo zero para prototipação e hospedagem inicial. | D30: João Lucas | F30: Ata de Validação de Escopo e TAP v1.2 (18/08/2026) | G30: Orçamento de referência: R$ 0,00
A31: Restrição | B31: Mudanças relevantes em escopo, prazo, custo, qualidade ou entregas somente via solicitação de mudança, dentro dos limites TRL 4–5. | D31: Arthur Laranjeira / Prof. Sandro Amâncio de Sá | F31: Ata de Validação de Escopo e TAP v1.2 (18/08/2026) | G31: Baixo impacto: aprovação do gerente; impacto em escopo/prazo/entregas: ciência do parceiro e aprovação do docente/PMO
A34: 5. Critérios de sucesso e marcos
A35: # | B35: Critério/Marco | C35: Métrica ou condição | D35: Data planejada | E35: Data real | F35: Status | G35: Aceite/registro
A36: 1 | B36: Parceria aceita formalmente | C36: Parceiro consultado presencialmente e aceite registrado | E36: 46252 | F36: Concluído | G36: Diário de bordo — Entrada 2
A37: 2 | B37: Reunião de diagnóstico com o parceiro | C37: Problema e necessidade confirmados | E37: 46252 | F37: Concluído | G37: Diário de bordo — Entrada 2
A38: 3 | B38: TAP v1.2 e linha de base aprovados | C38: Ata de validação de escopo aprovada | E38: 46252 | F38: Concluído | G38: Ata de Validação de Escopo e TAP — APROVADO, sem ressalvas
A39: 4 | B39: Planejamento consolidado | C39: TAP, escopo, cronograma e riscos aprovados | D39: 46253
A40: 5 | B40: Protótipo validado | C40: Feedback do parceiro registrado sobre o layout da landing page | D40: 46280 | G40: Reunião prevista para 12/09/2026 (Diário — Entrada 4, a confirmar)
A41: 6 | B41: MVP / testes | C41: Testes funcionais, de usabilidade e links do WhatsApp testados | D41: 46315
A42: 7 | B42: Encerramento | C42: Aceite/encerramento assinado pelo parceiro e entrega acadêmica | D42: 46341
A43: 8

Sheet 3. Stakeholders
A1: Registro de Stakeholders
A2: Mapeamento de poder, interesse, atitude e engajamento
A4: ID | B4: Stakeholder/Grupo | C4: Organização | D4: Papel/Interesse | E4: Poder (1-5) | F4: Interesse (1-5) | G4: Atitude | H4: Estratégia de engajamento | I4: Responsável | J4: Canal/Frequência
A5: STK-01 | B5: Daniel Laranjeira | C5: Restauração de Pisos de Madeira (autônomo) | D5: Organização parceira: valida requisitos, escopo e protótipo; fornece conteúdo (fotos e descrições) e feedback; opera o WhatsApp comercial | H5: Validar escopo, protótipo e aceite nos marcos; sessão presencial para coleta de fotos | I5: Arthur Laranjeira | J5: Reunião presencial em Ibiúna/SP (preferência aos sábados)
A6: STK-02 | B6: Arthur Laranjeira | C6: Equipe discente / Parceiro | D6: Gerente do projeto, sponsor e responsável de contato com o parceiro | H6: Integrar planejamento, cronograma, riscos, comunicação e evidências | I6: Arthur Laranjeira | J6: Reuniões da equipe e contato direto com o parceiro
A7: STK-03 | B7: Prof. Sandro Amâncio de Sá | C7: Fatec São Roque | D7: Docente / Sponsor institucional / PMO: orienta, acompanha a governança e aprova mudanças acadêmicas | H7: Reportar status, evidências e mudanças; solicitar aprovação de mudanças com impacto | I7: Arthur Laranjeira | J7: Aulas da disciplina e documentação do projeto
A8: STK-04 | B8: Equipe discente (Lucas De Gois, Gabriel Candido, João Lucas) | C8: Fatec São Roque (alunos) | D8: Planejar, prototipar, desenvolver, testar, documentar e registrar o trabalho | H8: Distribuir papéis e tarefas; acompanhar pelo quadro Kanban | I8: Arthur Laranjeira | J8: Quadro Trello/Kanban e reuniões da equipe
A9: STK-05 | B9: Proprietários de residências, sítios e chácaras de Ibiúna e região | C9: Comunidade / clientes potenciais | D9: Beneficiários: encontrar mão de obra qualificada e ver a qualidade das restaurações na internet | H9: Atendidos indiretamente pela landing page, galeria e canal de WhatsApp | I9: Daniel Laranjeira | J9: Landing page e WhatsApp comercial
A10: STK-06
A11: STK-07
A12: STK-08
A13: STK-09
A14: STK-10
A15: STK-11
A16: STK-12
A17: STK-13
A18: STK-14
A19: STK-15
A20: STK-16
A21: STK-17
... A26: Fonte: Ata de Validação de Escopo/TAP v1.2 e Diário de Bordo. Poder, interesse e atitude não constam nos documentos — preencher pela equipe.

Sheet 4. Requisitos
A1: Documento de Requisitos
A2: A coluna ODS/meta é obrigatória quando houver vínculo — ex.: 12.5, 9.3, 17.17
A4: ID | B4: Tipo | C4: Descrição do requisito | D4: Origem | E4: Prioridade | F4: Critério de aceitação | G4: ODS | H4: Meta ODS | I4: MVP? | J4: Responsável | K4: Status | L4: Evidência
A5: RF-01 | B5: Funcional | C5: Página com exibição dos tipos de restauração e acabamentos | D5: Parceiro (Daniel Laranjeira) | E5: Must | F5: Apresentar descrições claras e fotos dos serviços de madeira | G5: ODS 9 | H5: 9.c | I5: Sim | L5: Ata de Validação de Escopo e TAP v1.2 (18/08/2026)
A6: RF-02 | B6: Funcional | C6: Galeria de 'Antes e Depois' com fotos de projetos reais | D6: Parceiro (Daniel Laranjeira) | E6: Must | F6: Visualização nítida em carrossel/grade em dispositivos móveis | G6: ODS 12 | H6: 12.5 | I6: Sim | L6: Ata de Validação de Escopo e TAP v1.2 (18/08/2026)
A7: RF-03 | B7: Funcional | C7: Botão flutuante e de rodapé integrado ao WhatsApp | D7: Parceiro (Daniel Laranjeira) | E7: Must | F7: Ao clicar, abrir conversa já com mensagem inicial pré-formatada | G7: ODS 17 | H7: 17.17 | I7: Sim | L7: Ata de Validação de Escopo e TAP v1.2 (18/08/2026)
A8: RNF-01 | B8: Não funcional | C8: Design responsivo e alta performance de carregamento | D8: Parceiro (Daniel Laranjeira) | E8: Should | F8: Pontuação mobile satisfatória no PageSpeed e layout adaptado | G8: ODS 9 | H8: 9.c | I8: Sim | L8: Ata de Validação de Escopo e TAP v1.2 (18/08/2026)

Sheet 5. EAP-RACI
A1: EAP / WBS e Matriz de Responsabilidades
A2: Decomposição por entregas + responsáveis
A4: Código EAP | B4: Entrega | C4: Pacote de trabalho | D4: Atividade | E4: Esforço planej. (h) | F4: Responsável (R) | G4: Aprovador (A) | H4: Consultado (C) | I4: Informado (I) | J4: Unidade | K4: Status | L4: % concluído
A5: 1.1.1 | B5: 1. Iniciação | C5: Seleção do parceiro e governança | D5: Justificativa de seleção direta do parceiro, governança mínima e roteiro de primeiro contato | F5: Arthur Laranjeira | K5: Concluído | L5: 1
A6: 1.1.2 | B6: 1. Iniciação | C6: Diagnóstico | D6: Reunião de diagnóstico e alinhamento inicial com o parceiro | F6: Arthur Laranjeira | G6: Daniel Laranjeira | K6: Concluído | L6: 1
A7: 1.1.3 | B7: 1. Iniciação | C7: TAP | D7: Ata de validação de escopo e TAP v1.2 | F7: Arthur Laranjeira | G7: Daniel Laranjeira | K7: Concluído | L7: 1
A8: 1.2.1 | B8: 2. Planejamento | C8: Requisitos | D8: Documento de requisitos e rastreabilidade ODS/meta | G8: Daniel Laranjeira
A9: 1.2.2 | B9: 2. Planejamento | C9: Stakeholders | D9: Registro de stakeholders | F9: Arthur Laranjeira
A10: 1.2.3 | B10: 2. Planejamento | C10: Escopo, EAP e RACI | D10: Declaração de escopo, EAP/WBS e matriz RACI | F10: Arthur Laranjeira
A11: 1.2.4 | B11: 2. Planejamento | C11: Cronograma | D11: Cronograma, marcos e estimativas | F11: Arthur Laranjeira
A12: 1.2.5 | B12: 2. Planejamento | C12: Riscos e comunicação | D12: Registro de riscos e plano de comunicação | F12: Arthur Laranjeira
A13: 1.2.6 | B13: 2. Planejamento | C13: Orçamento | D13: Orçamento de referência (R$ 0,00) e ferramentas de custo zero | F13: João Lucas
A14: 1.2.7 | B14: 2. Planejamento | C14: Backlog | D14: Estruturação do backlog de requisitos e tarefas no quadro Kanban | F14: Lucas De Gois; João Lucas
A15: 2.1.1 | B15: 3. Conteúdo | C15: Coleta de conteúdo | D15: Coleta de imagens de serviços anteriores e depoimentos | F15: Arthur Laranjeira
A16: 2.2.1 | B16: 4. Protótipo | C16: Wireframe | D16: Wireframe / protótipo de baixa fidelidade (Figma) | F16: Gabriel Candido
A17: 2.2.2 | B17: 4. Protótipo | C17: Validação | D17: Validação do protótipo navegável com o parceiro (layout, cores, galeria e CTA) | F17: Gabriel Candido | G17: Daniel Laranjeira
A18: 2.3.1 | B18: 5. MVP | C18: Landing page | D18: Landing page responsiva (Home, Sobre, Serviços, Galeria, Contato) | G18: Daniel Laranjeira
A19: 2.3.2 | B19: 5. MVP | C19: Galeria | D19: Galeria interativa 'Antes e Depois' | G19: Daniel Laranjeira
A20: 2.3.3 | B20: 5. MVP | C20: WhatsApp | D20: Botões de CTA integrados ao WhatsApp comercial | G20: Daniel Laranjeira
A21: 2.3.4 | B21: 5. MVP | C21: SEO e publicação | D21: SEO básico local e hospedagem/publicação do MVP
A22: 2.4.1 | B22: 6. Testes | C22: Testes | D22: Testes funcionais, de usabilidade, links do WhatsApp e cross-browser | F22: Gabriel Candido
A23: 3.1 | B23: 7. Encerramento | C23: Documentação | D23: Relatórios de testes, indicadores, documentação técnica e portfólio final
A24: 3.2 | B24: 7. Encerramento | C24: Aceite | D24: Aceite/encerramento assinado pelo parceiro e entrega acadêmica | F24: Arthur Laranjeira | G24: Daniel Laranjeira
A45: Fonte: entregáveis aprovados na Ata/TAP v1.2, pendências e marcos. Esforço (h), Consultado/Informado e unidade não constam nos documentos — preencher pela equipe.

Sheet 6. Cronograma
A1: Cronograma do Projeto
A2: Planejamento x execução e progresso
A4: ID | B4: Atividade/Marco | C4: Unidade | D4: Início planej. | E4: Fim planej. | F4: Início real | G4: Fim real | H4: % concluído | I4: Dependência | J4: Responsável
A5: 1 | B5: Reunião interna da equipe — seleção do parceiro e governança | F5: 46252 | G5: 46252 | H5: 1 | J5: Arthur Laranjeira
A6: 2 | B6: Reunião de diagnóstico e alinhamento inicial com o parceiro | F6: 46252 | G6: 46252 | H6: 1 | I6: 1 | J6: Arthur Laranjeira
A7: 3 | B7: Reunião de validação de escopo e TAP v1.2 (marco) | F7: 46252 | G7: 46252 | H7: 1 | I7: 2 | J7: Arthur Laranjeira
A8: 4 | B8: Planejamento consolidado (marco) | E8: 46253 | I8: 3 | J8: Arthur Laranjeira
A9: 5 | B9: Coleta de imagens de serviços anteriores e depoimentos | E9: 46259 | I9: 3 | J9: Arthur Laranjeira
A10: 6 | B10: Estruturação do backlog de requisitos e tarefas | E10: 46266 | I10: 3 | J10: Lucas De Gois; João Lucas
A11: 7 | B11: Wireframe / protótipo de baixa fidelidade | E11: 46270 | I11: 5 | J11: Gabriel Candido
A12: 8 | B12: Reunião de validação do protótipo com o parceiro (data a confirmar) | D12: 46277 | E12: 46277 | I12: 7 | J12: Arthur Laranjeira; Gabriel Candido
A13: 9 | B13: Protótipo validado (marco) | E13: 46280 | I13: 8 | J13: Gabriel Candido
A14: 10 | B14: MVP / testes (marco) | E14: 46315 | I14: 9 | J14: Equipe discente
A15: 11 | B15: Encerramento (marco) | E15: 46341 | I15: 10 | J15: Arthur Laranjeira
A45: Fonte: marcos e pendências da Ata/TAP v1.2 e Diário de Bordo. Datas de início planejadas e progresso das atividades futuras não constam nos documentos.

Sheet 7. Orçamento
A1: Orçamento e Cotações
A2: Previsto x real; base para o indicador ODS 9.3.1
A4: ID | B4: Categoria | C4: Item/Serviço | D4: Qtd. | E4: Custo unit. previsto | F4: Custo previsto | G4: Custo real | H4: Variação | I4: Fonte/Cotação | J4: Observação
A5: 1 | B5: Desenvolvimento | C5: Desenvolvimento da landing page (execução acadêmica) | D5: 1 | E5: 0 | F5: =IFERROR(D5*E5,0) | G5: 0 | H5: =IFERROR(G5-F5,0) | I5: TAP v1.2 — item 11 | J5: Sem custos diretos de desenvolvimento
A6: 2 | B6: Hospedagem e infraestrutura | C6: Hospedagem do MVP (GitHub Pages / Vercel / Netlify) | D6: 1 | E6: 0 | F6: =IFERROR(D6*E6,0) | G6: 0 | H6: =IFERROR(G6-F6,0) | I6: TAP v1.2 — item 11 | J6: Plataforma gratuita
A7: 3 | B7: Software/SaaS | C7: Domínio temporário | D7: 1 | E7: 0 | F7: =IFERROR(D7*E7,0) | G7: 0 | H7: =IFERROR(G7-F7,0) | I7: TAP v1.2 — item 11 | J7: Domínio temporário gratuito
A8: 4 | D8: 1 | F8: =IFERROR(D8*E8,0) | H8: =IFERROR(G8-F8,0)
A9: 5 | D9: 1 | F9: =IFERROR(D9*E9,0) | H9: =IFERROR(G9-F9,0)
A10: 6 | D10: 1 | F10: =IFERROR(D10*E10,0) | H10: =IFERROR(G10-F10,0)
A11: 7 | D11: 1 | F11: =IFERROR(D11*E11,0) | H11: =IFERROR(G11-F11,0)
A12: 8 | D12: 1 | F12: =IFERROR(D12*E12,0) | H12: =IFERROR(G12-F12,0)
A13: 9 | D13: 1 | F13: =IFERROR(D13*E13,0) | H13: =IFERROR(G13-F13,0)
A14: 10 | D14: 1 | F14: =IFERROR(D14*E14,0) | H14: =IFERROR(G14-F14,0)
A15: 11 | D15: 1 | F15: =IFERROR(D15*E15,0) | H15: =IFERROR(G15-F15,0)
A16: 12 | D16: 1 | F16: =IFERROR(D16*E16,0) | H16: =IFERROR(G16-F16,0)
A17: 13 | D17: 1 | F17: =IFERROR(D17*E17,0) | H17: =IFERROR(G17-F17,0)
A18: 14 | D18: 1 | F18: =IFERROR(D18*E18,0) | H18: =IFERROR(G18-F18,0)
A19: 15 | D19: 1 | F19: =IFERROR(D19*E19,0) | H19: =IFERROR(G19-F19,0)
... A33: 29 | D33: 1 | F33: =IFERROR(D33*E33,0) | H33: =IFERROR(G33-F33,0)
A36: RESUMO
A37: Custo previsto total | B37: =SUM(F5:F33)
A38: Custo real total | B38: =SUM(G5:G33)
A39: Variação total | B39: =B38-B37
A40: Média 3 cotações mercado
A41: Economia estimada ao parceiro | B41: =MAX(B40-B37,0)

Sheet 8. Riscos
A1: Registro de Riscos e Problemas
A2: Probabilidade × impacto, resposta, proprietário e gatilho
A4: ID | B4: Tipo | C4: Risco/Problema | D4: Causa | E4: Prob. (1-5) | F4: Impacto (1-5) | G4: Exposição | H4: Resposta | I4: Proprietário | J4: Gatilho | K4: Status
A5: R01 | B5: Risco | C5: Demora no fornecimento das fotos e descrições dos serviços pelo parceiro | D5: Dependência de conteúdo do parceiro para a galeria | G5: =IFERROR(E5*F5,0) | H5: Mitigar: agendar sessão presencial de coleta | I5: Arthur Laranjeira | J5: Fotos não recebidas até 25/08/2026
A6: R02 | B6: Risco | C6: Incompatibilidade de visualização em determinados navegadores móveis | D6: Diferenças entre navegadores e dispositivos | G6: =IFERROR(E6*F6,0) | H6: Mitigar: testes cross-browser | I6: Gabriel Candido | J6: Erro de exibição em dispositivo móvel do parceiro
A7: R03 | B7: Risco | G7: =IFERROR(E7*F7,0) | K7: Não iniciado
A8: R04 | B8: Risco | G8: =IFERROR(E8*F8,0) | K8: Não iniciado
A9: R05 | B9: Risco | G9: =IFERROR(E9*F9,0) | K9: Não iniciado
A10: R06 | B10: Risco | G10: =IFERROR(E10*F10,0) | K10: Não iniciado
A11: R07 | B11: Risco | G11: =IFERROR(E11*F11,0) | K11: Não iniciado
A12: R08 | B12: Risco | G12: =IFERROR(E12*F12,0) | K12: Não iniciado
A13: R09 | B13: Risco | G13: =IFERROR(E13*F13,0) | K13: Não iniciado
A14: R10 | B14: Risco | G14: =IFERROR(E14*F14,0) | K14: Não iniciado
A15: R11 | B15: Risco | G15: =IFERROR(E15*F15,0) | K15: Não iniciado
A16: R12 | B16: Risco | G16: =IFERROR(E16*F16,0) | K16: Não iniciado
A17: R13 | B17: Risco | G17: =IFERROR(E17*F17,0) | K17: Não iniciado
A18: R14 | B18: Risco | G18: =IFERROR(E18*F18,0) | K18: Não iniciado
... A33: R29 | B33: Risco | G33: =IFERROR(E33*F33,0) | K33: Não iniciado
A35: Fonte: riscos iniciais da Ata/TAP v1.2. Probabilidade e impacto não constam nos documentos — preencher pela equipe para calcular a exposição.

Sheet 9. Backlog-Sprints
A1: Backlog do Produto e Sprints
A2: Pode ser espelhado do Jira; mantenha o link na aba Identificação
A4: ID | B4: Épico | C4: História/Tarefa | D4: Critério de aceitação | E4: Prioridade | F4: Story points | G4: Sprint | H4: Responsável | I4: Status | J4: Início | K4: Fim | L4: Chave Jira | M4: URL Jira | N4: Status Jira (retorno) | O4: Último status sincronizado | P4: Ação de sincronização | Q4: Última sincronização | R4: Resultado da sincronização
A5: PB-001 | B5: Landing page | C5: RF-01 — Página com exibição dos tipos de restauração e acabamentos | D5: Apresentar descrições claras e fotos dos serviços de madeira | E5: Must
A6: PB-002 | B6: Galeria Antes e Depois | C6: RF-02 — Galeria de 'Antes e Depois' com fotos de projetos reais | D6: Visualização nítida em carrossel/grade em dispositivos móveis | E6: Must
A7: PB-003 | B7: Canal WhatsApp | C7: RF-03 — Botão flutuante e de rodapé integrado ao WhatsApp | D7: Ao clicar, abrir conversa já com mensagem inicial pré-formatada | E7: Must
A8: PB-004 | B8: Landing page | C8: RNF-01 — Design responsivo e alta performance de carregamento | D8: Pontuação mobile satisfatória no PageSpeed e layout adaptado | E8: Should
A9: PB-005 | B9: Conteúdo | C9: Coleta de imagens de serviços anteriores e depoimentos | D9: Fotos e depoimentos arquivados na pasta do Drive | H9: Arthur Laranjeira | K9: 46259
A10: PB-006 | B10: Protótipo | C10: Wireframe / protótipo de baixa fidelidade | D10: Protótipo disponível em link do Figma | H10: Gabriel Candido | K10: 46270
A11: PB-007 | B11: Gestão do projeto | C11: Estruturação do backlog de requisitos e tarefas | D11: Quadro Trello/Kanban com requisitos e tarefas | H11: Lucas De Gois; João Lucas | K11: 46266
A12: PB-008 | B12: Landing page | C12: SEO básico para Ibiúna e região
A13: PB-009 | B13: Publicação | C13: Hospedagem e publicação do MVP em ambiente web acessível
A57: PB-001 a PB-004 correspondem aos requisitos RF-01, RF-02, RF-03 e RNF-01; PB-005 a PB-007 vêm das pendências da Ata/TAP; PB-008 e PB-009 vêm do escopo incluído.

Sheet 10. Horas Extensão
A1: Controle de Horas de Extensão — Equipe
A2: Preencher a cada atividade; anexar link/arquivo de evidência
A4: # | B4: Data | C4: Unidade | D4: Atividade | E4: Etapa | F4: h em aula | G4: h extraclasse | H4: Total h | I4: Participantes | J4: Evidência | K4: Validação professor
A5: 1 | B5: 46252 | D5: Reunião interna da equipe: viabilidade do parceiro, justificativa de seleção direta, governança e roteiro de primeiro contato | H5: =SUM(F5:G5) | I5: Arthur Laranjeira; Lucas De Gois; Gabriel Candido; João Lucas | J5: Diário de bordo — Entrada 1 | K5: Pendente
A6: 2 | B6: 46252 | D6: Reunião de diagnóstico e alinhamento inicial com o parceiro (presencial em Ibiúna/SP) | H6: =SUM(F6:G6) | I6: Arthur Laranjeira | J6: Diário de bordo — Entrada 2 | K6: Pendente
A7: 3 | B7: 46252 | D7: Reunião de validação de escopo e TAP v1.2 (presencial em Ibiúna/SP, 10h00) | H7: =SUM(F7:G7) | I7: Arthur Laranjeira (presente); Lucas De Gois, Gabriel Candido, João Lucas e Prof. Sandro Amâncio de Sá (convocados) | J7: Ata de Validação de Escopo e TAP v1.2 | K7: Pendente
A8: 4 | H8: =SUM(F8:G8) | K8: Pendente
A9: 5 | H9: =SUM(F9:G9) | K9: Pendente
A10: 6 | H10: =SUM(F10:G10) | K10: Pendente
A11: 7 | H11: =SUM(F11:G11) | K11: Pendente
A12: 8 | H12: =SUM(F12:G12) | K12: Pendente
A13: 9 | H13: =SUM(F13:G13) | K13: Pendente
A14: 10 | H14: =SUM(F14:G14) | K14: Pendente
A15: 11 | H15: =SUM(F15:G15) | K15: Pendente
A16: 12 | H16: =SUM(F16:G16) | K16: Pendente
A17: 13 | H17: =SUM(F17:G17) | K17: Pendente
A18: 14 | H18: =SUM(F18:G18) | K18: Pendente
A19: 15 | H19: =SUM(F19:G19) | K19: Pendente
... A63: 59 | H63: =SUM(F63:G63) | K63: Pendente
A66: RESUMO DE HORAS
A67: Horas em aula | B67: =SUM(F5:F63)
A68: Horas extraclasse | B68: =SUM(G5:G63)
A69: Total registrado | B69: =SUM(H5:H63)
A70: Meta de extensão | B70: 60
A71: Atingimento da meta | B71: =IFERROR(B69/B70,0)

Sheet 11. Mudanças
A1: Controle Integrado de Mudanças
A2: Registrar solicitações do parceiro e mudanças simuladas pelo docente
A4: ID | B4: Data | C4: Solicitante | D4: Mudança solicitada | E4: Impacto escopo | F4: Impacto prazo | G4: Impacto custo | H4: Impacto qualidade | I4: Decisão | J4: Aprovador | K4: Data decisão | L4: Evidência

Sheet 12. Qualidade-Testes
A1: Qualidade, Critérios de Aceitação e Testes
A2: Use dados fictícios quando houver informação pessoal/sensível
A4: ID | B4: Requisito | C4: Tipo de teste | D4: Cenário/Tarefa | E4: Resultado esperado | F4: Resultado obtido | G4: Status | H4: Severidade defeito | I4: Responsável | J4: Data | K4: Usuário real? | L4: Evidência
A5: TC-001 | B5: RF-01 — Serviços | C5: Funcional | D5: Abrir a página de serviços | E5: Descrições claras e fotos dos serviços de madeira exibidas | G5: Não executado
A6: TC-002 | B6: RF-02 — Galeria | C6: Usabilidade | D6: Navegar pela galeria 'Antes e Depois' em um celular | E6: Visualização nítida em carrossel/grade | G6: Não executado
A7: TC-003 | B7: RF-03 — WhatsApp | C7: Funcional | D7: Clicar no botão flutuante e no botão de rodapé do WhatsApp | E7: Conversa aberta com mensagem inicial pré-formatada | G7: Não executado
A8: TC-004 | B8: RNF-01 — Desempenho | C8: Desempenho | D8: Medir a página no PageSpeed (mobile) | E8: Pontuação mobile satisfatória e carregamento em menos de 3 s | G8: Não executado
A9: TC-005 | B9: RNF-01 — Compatibilidade | C9: Compatibilidade | D9: Abrir a landing page em diferentes navegadores móveis, incluindo o dispositivo do parceiro | E9: Layout adaptado e exibição correta | G9: Não executado

Sheet 13. EVM
A1: Earned Value Management (EVM)
A2: PV = Planned Value · EV = Earned Value · AC = Actual Cost
A4: Período | B4: PV | C4: EV | D4: AC | E4: CV = EV-AC | F4: SV = EV-PV | G4: CPI = EV/AC | H4: SPI = EV/PV | I4: Situação custo | J4: Situação prazo
A5: P1 | E5: =IFERROR(C5-D5,0) | F5: =IFERROR(C5-B5,0) | G5: =IFERROR(C5/D5,0) | H5: =IFERROR(C5/B5,0) | I5: =IF(G5>=1,"Dentro/abaixo","Acima do custo") | J5: =IF(H5>=1,"No prazo/adiantado","Atrasado")
A6: P2 | E6: =IFERROR(C6-D6,0) | F6: =IFERROR(C6-B6,0) | G6: =IFERROR(C6/D6,0) | H6: =IFERROR(C6/B6,0) | I6: =IF(G6>=1,"Dentro/abaixo","Acima do custo") | J6: =IF(H6>=1,"No prazo/adiantado","Atrasado")
A7: P3 | E7: =IFERROR(C7-D7,0) | F7: =IFERROR(C7-B7,0) | G7: =IFERROR(C7/D7,0) | H7: =IFERROR(C7/B7,0) | I7: =IF(G7>=1,"Dentro/abaixo","Acima do custo") | J7: =IF(H7>=1,"No prazo/adiantado","Atrasado")
A8: P4 | E8: =IFERROR(C8-D8,0) | F8: =IFERROR(C8-B8,0) | G8: =IFERROR(C8/D8,0) | H8: =IFERROR(C8/B8,0) | I8: =IF(G8>=1,"Dentro/abaixo","Acima do custo") | J8: =IF(H8>=1,"No prazo/adiantado","Atrasado")
A9: P5 | E9: =IFERROR(C9-D9,0) | F9: =IFERROR(C9-B9,0) | G9: =IFERROR(C9/D9,0) | H9: =IFERROR(C9/B9,0) | I9: =IF(G9>=1,"Dentro/abaixo","Acima do custo") | J9: =IF(H9>=1,"No prazo/adiantado","Atrasado")
A10: P6 | E10: =IFERROR(C10-D10,0) | F10: =IFERROR(C10-B10,0) | G10: =IFERROR(C10/D10,0) | H10: =IFERROR(C10/B10,0) | I10: =IF(G10>=1,"Dentro/abaixo","Acima do custo") | J10: =IF(H10>=1,"No prazo/adiantado","Atrasado")
A11: P7 | E11: =IFERROR(C11-D11,0) | F11: =IFERROR(C11-B11,0) | G11: =IFERROR(C11/D11,0) | H11: =IFERROR(C11/B11,0) | I11: =IF(G11>=1,"Dentro/abaixo","Acima do custo") | J11: =IF(H11>=1,"No prazo/adiantado","Atrasado")
A12: P8 | E12: =IFERROR(C12-D12,0) | F12: =IFERROR(C12-B12,0) | G12: =IFERROR(C12/D12,0) | H12: =IFERROR(C12/B12,0) | I12: =IF(G12>=1,"Dentro/abaixo","Acima do custo") | J12: =IF(H12>=1,"No prazo/adiantado","Atrasado")
A13: P9 | E13: =IFERROR(C13-D13,0) | F13: =IFERROR(C13-B13,0) | G13: =IFERROR(C13/D13,0) | H13: =IFERROR(C13/B13,0) | I13: =IF(G13>=1,"Dentro/abaixo","Acima do custo") | J13: =IF(H13>=1,"No prazo/adiantado","Atrasado")
A14: P10 | E14: =IFERROR(C14-D14,0) | F14: =IFERROR(C14-B14,0) | G14: =IFERROR(C14/D14,0) | H14: =IFERROR(C14/B14,0) | I14: =IF(G14>=1,"Dentro/abaixo","Acima do custo") | J14: =IF(H14>=1,"No prazo/adiantado","Atrasado")
A15: P11 | E15: =IFERROR(C15-D15,0) | F15: =IFERROR(C15-B15,0) | G15: =IFERROR(C15/D15,0) | H15: =IFERROR(C15/B15,0) | I15: =IF(G15>=1,"Dentro/abaixo","Acima do custo") | J15: =IF(H15>=1,"No prazo/adiantado","Atrasado")
A16: P12 | E16: =IFERROR(C16-D16,0) | F16: =IFERROR(C16-B16,0) | G16: =IFERROR(C16/D16,0) | H16: =IFERROR(C16/B16,0) | I16: =IF(G16>=1,"Dentro/abaixo","Acima do custo") | J16: =IF(H16>=1,"No prazo/adiantado","Atrasado")
... A23: P19 | E23: =IFERROR(C23-D23,0) | F23: =IFERROR(C23-B23,0) | G23: =IFERROR(C23/D23,0) | H23: =IFERROR(C23/B23,0) | I23: =IF(G23>=1,"Dentro/abaixo","Acima do custo") | J23: =IF(H23>=1,"No prazo/adiantado","Atrasado")
A26: RESUMO EVM
A27: PV acumulado | B27: =SUM(B5:B23)
A28: EV acumulado | B28: =SUM(C5:C23)
A29: AC acumulado | B29: =SUM(D5:D23)
A30: CPI | B30: =IFERROR(B28/B29,0)
A31: SPI | B31: =IFERROR(B28/B27,0)
A32: Situação custo | B32: =IF(B30>=1,"Dentro/abaixo do custo","Acima do custo")
A33: Situação prazo | B33: =IF(B31>=1,"No prazo/adiantado","Atrasado")

Sheet 14. Indicadores ODS
A1: Indicadores ODS e Indicadores Discentes
A2: Cálculos consolidados para a Unidade 19
A4: Indicador | B4: Entrada 1 | C4: Entrada 2 | D4: Entrada 3 | E4: Resultado | F4: Classificação/Nota
A5: I_9.3.1 — valor adicionado | B5: =IF('7. Orçamento'!B37=0,"",'7. Orçamento'!B37) | C5: =IF('7. Orçamento'!B40=0,"",'7. Orçamento'!B40) | D5: — | E5: =IF(C5="","",IFERROR(B5/C5,0)) | F5: =IF(E5="","",IF(E5<=0.4,"Excelente",IF(E5<=0.7,"Adequado","Insuficiente")))
A6: Nota normalizada 9.3.1 | B6: — | C6: — | D6: — | E6: =IF(E5="","",MAX(MIN(1-E5,1),0)) | F6: =IF(E6="","",E6)
A7: I_12.b.1 — desempenho EVM | B7: =IF('13. EVM'!B30=0,"",'13. EVM'!B30) | C7: =IF('13. EVM'!B31=0,"",'13. EVM'!B31) | D7: — | E7: =IF(OR(B7="",C7=""),"",IFERROR((B7+C7)/2,0)) | F7: =IF(E7="","",IF(E7>=0.95,"Excelente",IF(E7>=0.85,"Adequado","Insuficiente")))
A8: Conformidade instrumentos | C8: — | D8: — | E8: =IF(B8="","",IFERROR(B8/5,0)) | F8: =IF(E8="","",E8)
A9: I_17.18.1 — requisitos com ODS | B9: 4 | C9: 4 | D9: — | E9: =IF(C9="","",IFERROR(B9/C9,0)) | F9: =IF(E9="","",IF(E9>=0.5,"Excelente",IF(E9>=0.3,"Adequado","Insuficiente")))
A10: Eficiência discente | E10: =IF(OR(B10="",C10="",D10=""),"",IFERROR((B10/C10)/D10,0)) | F10: =IF(E10="","",E10)
A11: Eficácia discente | D11: — | E11: =IF(C11="","",IFERROR(B11/C11,0)) | F11: =IF(E11="","",E11)
A14: RESUMO PARA ENTREGA
A15: CPI | B15: =B7
A16: SPI | B16: =C7
A17: I_9.3.1 | B17: =E5
A18: I_12.b.1 | B18: =E7
A19: I_17.18.1 | B19: =E9
A20: Eficiência | B20: =E10
A21: Eficácia | B21: =E11

Sheet 15. Evidências
A1: Matriz de Evidências do Projeto
A2: Consolide links, arquivos e aceite; a entrega final deve permanecer arquivável
A4: Categoria | B4: Evidência | C4: Unidade/Prazo | D4: Responsável | E4: Link/Arquivo | F4: Status | G4: Data | H4: Observação
A5: Institucional | B5: Termo de anuência do parceiro | C5: Pré | D5: Arthur Laranjeira | E5: Diário de bordo — Entrada 2 | F5: Concluído | G5: 46252 | H5: Parceiro aceitou formalmente a parceria em reunião presencial
A6: Iniciação | B6: Dossiê de contexto do parceiro | C6: 1
A7: Iniciação | B7: Documento de requisitos com ODS/meta | C7: 3 | D7: Lucas De Gois; João Lucas | E7: Repositório do Projeto / Documentação
A8: Iniciação | B8: TAP assinado | C8: 12 | D8: Arthur Laranjeira | E8: TAP_PisoFacil_v1.2.docx / Ata assinada na Pasta Google Drive | F8: Concluído | G8: 46252 | H8: TAP aprovado sem ressalvas
A9: Planejamento | B9: Registro de stakeholders | C9: 12
A10: Planejamento | B10: EAP/WBS | C10: 17 | D10: Arthur Laranjeira | E10: Planejamento integrado da disciplina
A11: Planejamento | B11: Cronograma | C11: 17 | D11: Arthur Laranjeira | E11: Planejamento integrado da disciplina
A12: Planejamento | B12: Orçamento e cotações | C12: 17
A13: Planejamento | B13: RACI | C13: 17 | D13: Arthur Laranjeira | E13: Planejamento integrado da disciplina
A14: Planejamento | B14: Plano de comunicação | C14: 17
A15: Planejamento | B15: Registro de riscos | C15: 17
A16: Execução | B16: Board Kanban / backlog | C16: 13 | D16: Lucas De Gois; João Lucas | E16: Quadro Trello/Kanban | H16: Previsto para 01/09/2026
A17: Produto | B17: Protótipo navegável | C17: 18 | D17: Gabriel Candido | E17: Link Figma | H17: Wireframe previsto para 05/09/2026
A18: Produto | B18: MVP / repositório GitHub | C18: 18
A19: Produto | B19: Homologação acessível ao parceiro | C19: 18
A20: Produto | B20: Relatório de teste com 3–5 usuários | C20: 18-19
A21: Execução | B21: Atas e relatórios de status | C21: 18 | D21: Arthur Laranjeira | E21: Quadro Kanban / Diário de Bordo do Projeto
A22: Execução | B22: Registro de mudanças | C22: 18
A23: Encerramento | B23: EVM | C23: 19
A24: Indicadores | B24: Ficha de indicadores ODS | C24: 19
A25: Encerramento | B25: Termo de aceite/encerramento | C25: 19
A26: Encerramento | B26: Lições aprendidas | C26: 19
A27: Divulgação | B27: Apresentação final | C27: 20
A28: Divulgação | B28: Fotos/vídeos autorizados | C28: 20 | D28: Arthur Laranjeira | E28: Registro fotográfico / Arquivo da equipe
A29: Divulgação | B29: Portfólio final | C29: 20

Sheet 16. Encerramento
A1: Encerramento do Projeto
A2: Aceite, resultados, lições aprendidas e continuidade
A4: AVALIAÇÃO DOS OBJETIVOS
A5: # | B5: Objetivo | C5: Indicador | D5: Meta | E5: Resultado | F5: Status | G5: Validação parceiro | H5: Evidência
A6: 1 | B6: OBJ-01 — Landing page responsiva publicada | C6: Site publicado, responsivo e carregando em < 3 s | D6: Publicado até o encerramento do semestre
A7: 2 | B7: OBJ-02 — Catálogo interativo de antes e depois | C7: Galeria aprovada pelo parceiro no teste de usabilidade | D7: Mínimo de 6 projetos de restauro
A8: 3 | B8: OBJ-03 — Canal ágil de captação via WhatsApp | C8: Acionamento do CTA/WhatsApp nos testes de clique | D8: 100% dos testes de clique
A9: 4
A10: 5
A11: 6
A12: 7
A13: 8
A14: 9
A17: LIÇÕES APRENDIDAS
A18: Categoria | B18: O que aconteceu | C18: Impacto | D18: O que funcionou | E18: O que mudaríamos | F18: Responsável | G18: Ação futura | H18: Prazo
A19: Governança | B19: Seleção direta do parceiro, sem matriz comparativa formal | C19: Necessidade de transparência perante o docente e o PMO | D19: Registrar formalmente os critérios da escolha (valor social e viabilidade de comunicação)
A27: ACEITE E CONTINUIDADE
A28: MVP aceito pelo parceiro?
A29: TRL alcançado
A30: Pendências conhecidas | B30: Coleta de imagens e depoimentos (25/08); wireframe/protótipo (05/09); backlog no Kanban (01/09); registro da reunião de validação do protótipo (Diário — Entrada 4, a preencher)
A31: Recomendação de continuidade
A32: Responsável pela continuidade
A33: Termo de encerramento (link)
A34: Data do aceite | B34: Previsto: 15/11/2026
A35: Assinatura/validação parceiro | B35: Daniel Laranjeira (a validar)
A36: Observação final | B36: Preenchido a partir da Ata de Validação de Escopo/TAP v1.2 e do Diário de Bordo do PisoFácil. Campos sem informação nas fontes ficaram em branco para a equipe completar.

Sheet Dashboard
A1: Dashboard do Projeto
A2: Resumo executivo para acompanhamento da equipe e validação do professor
A4: KPIs
A5: Projeto | B5: =IF('1. Identificação'!B5="","",'1. Identificação'!B5) | C5: Parceiro | D5: =IF('1. Identificação'!B7="","",'1. Identificação'!B7) | E5: ODS | F5: =IF('1. Identificação'!B13="","",'1. Identificação'!B13)
A6: Horas registradas | B6: ='10. Horas Extensão'!B69 | C6: Meta | D6: 60 | E6: Atingimento | F6: =IFERROR(B6/D6,0)
A7: Progresso cronograma | B7: =IFERROR(AVERAGE('6. Cronograma'!H5:H43),0) | C7: Evidências concluídas | D7: =COUNTIF('15. Evidências'!F5:F29,"Concluído") | E7: Riscos altos/críticos | F7: =COUNTIF('8. Riscos'!G5:G33,">=15")
A8: CPI | B8: ='13. EVM'!B30 | C8: SPI | D8: ='13. EVM'!B31 | E8: TRL | F8: =IF('16. Encerramento'!B29="","",'16. Encerramento'!B29)
A11: INDICADORES ODS
A12: Indicador | B12: Resultado | C12: Classificação | D12: Fonte | E12: Situação | F12: Observação | H12: Status | I12: Quantidade
A13: ODS 9.3.1 | B13: ='14. Indicadores ODS'!E5 | C13: ='14. Indicadores ODS'!F5 | D13: Orçamento + 3 cotações | H13: Não iniciado | I13: =COUNTIF('9. Backlog-Sprints'!I5:I53,H13)
A14: ODS 12.b.1 | B14: ='14. Indicadores ODS'!E7 | C14: ='14. Indicadores ODS'!F7 | D14: EVM | H14: Em andamento | I14: =COUNTIF('9. Backlog-Sprints'!I5:I53,H14)
A15: ODS 17.18.1 | B15: ='14. Indicadores ODS'!E9 | C15: ='14. Indicadores ODS'!F9 | D15: Requisitos + ODS/meta | H15: Aguardando parceiro | I15: =COUNTIF('9. Backlog-Sprints'!I5:I53,H15)
A16: Eficiência / Eficácia | B16: =IF(COUNT('14. Indicadores ODS'!E10:E11)=0,"",AVERAGE('14. Indicadores ODS'!E10:E11)) | C16: =IF(B16="","",IF(B16>=0.95,"Excelente",IF(B16>=0.85,"Adequado","Atenção"))) | D16: EAP + horas + objetivos | H16: Concluído | I16: =COUNTIF('9. Backlog-Sprints'!I5:I53,H16)
H17: Bloqueado | I17: =COUNTIF('9. Backlog-Sprints'!I5:I53,H17)

Sheet Jira_teste_leitura
A1: key | B1: summary | C1: status | D1: assignee | E1: created | F1: updated | G1: assigneeAccountId | H1: id | I1: statusId | J1: link

Sheet Jira_consulta
A1: key | B1: summary | C1: status | D1: assignee | E1: created | F1: updated | G1: assigneeAccountId | H1: id | I1: statusId | J1: link

Sheet Função Invocada
A1: DadosExternos_2
